nimble-0.5.3.dist-info/RECORD
nimble-0.5.3.dist-info/LICENSE
nimble-0.5.3.dist-info/WHEEL
nimble-0.5.3.dist-info/top_level.txt
nimble-0.5.3.dist-info/METADATA
nimble/__init__.cpython-312-darwin.so
nimble/_utility.cpython-312-darwin.so
nimble/_dependencies.py
nimble/_utility.py
nimble/__init__.c
nimble/_dependencies.cpython-312-darwin.so
nimble/__init__.py
nimble/configuration.ini
nimble/_dependencies.c
nimble/_utility.c
nimble/exceptions.py
nimble/exceptions.c
nimble/exceptions.cpython-312-darwin.so
nimble/core/__init__.cpython-312-darwin.so
nimble/core/configuration.py
nimble/core/_learnHelpers.py
nimble/core/_learnHelpers.cpython-312-darwin.so
nimble/core/_createHelpers.py
nimble/core/create.cpython-312-darwin.so
nimble/core/create.py
nimble/core/tune.cpython-312-darwin.so
nimble/core/__init__.c
nimble/core/__init__.py
nimble/core/create.c
nimble/core/configuration.cpython-312-darwin.so
nimble/core/tune.py
nimble/core/tune.c
nimble/core/learn.py
nimble/core/_createHelpers.c
nimble/core/_learnHelpers.c
nimble/core/learn.c
nimble/core/learn.cpython-312-darwin.so
nimble/core/_createHelpers.cpython-312-darwin.so
nimble/core/configuration.c
nimble/core/logger/__init__.cpython-312-darwin.so
nimble/core/logger/session_logger.py
nimble/core/logger/__init__.c
nimble/core/logger/__init__.py
nimble/core/logger/session_logger.c
nimble/core/logger/session_logger.cpython-312-darwin.so
nimble/core/data/__init__.cpython-312-darwin.so
nimble/core/data/matrix.py
nimble/core/data/sparseAxis.py
nimble/core/data/list.c
nimble/core/data/axis.py
nimble/core/data/sparseAxis.cpython-312-darwin.so
nimble/core/data/views.cpython-312-darwin.so
nimble/core/data/points.py
nimble/core/data/stretch.py
nimble/core/data/list.py
nimble/core/data/matrixAxis.cpython-312-darwin.so
nimble/core/data/dataframe.cpython-312-darwin.so
nimble/core/data/views.c
nimble/core/data/dataframeAxis.py
nimble/core/data/dataframe.py
nimble/core/data/axis.cpython-312-darwin.so
nimble/core/data/sparse.c
nimble/core/data/points.c
nimble/core/data/dataframeAxis.cpython-312-darwin.so
