Metadata-Version: 2.1
Name: nimble
Version: 0.5.3
Summary: Interfaces and tools for data science.
Author-email: Spark Wave LLC <info@sparkwave.tech>
License: Apache 2.0
Project-URL: Homepage, https://www.nimbledata.org
Project-URL: Repository, https://github.com/willfind/nimble
Classifier: Development Status :: 5 - Production/Stable
Classifier: Programming Language :: Python :: 3
Classifier: Programming Language :: Python :: 3.8
Classifier: Programming Language :: Python :: 3.9
Classifier: Programming Language :: Python :: 3.10
Classifier: Programming Language :: Python :: 3.11
Classifier: Programming Language :: Python :: 3.12
Classifier: Operating System :: OS Independent
Classifier: License :: OSI Approved :: Apache Software License
Requires-Python: <3.13,>=3.8
License-File: LICENSE
Requires-Dist: numpy >=1.14
Requires-Dist: packaging >=20.0
Requires-Dist: tomli >=2.0
Requires-Dist: scipy >=1.1
Provides-Extra: all
Requires-Dist: pandas >=0.24 ; extra == 'all'
Requires-Dist: scipy >=1.1 ; extra == 'all'
Requires-Dist: matplotlib >=3.1 ; extra == 'all'
Requires-Dist: cloudpickle >=1.0 ; extra == 'all'
Requires-Dist: requests >2.12 ; extra == 'all'
Requires-Dist: h5py >=2.10 ; extra == 'all'
Requires-Dist: python-dateutil >=2.6 ; extra == 'all'
Requires-Dist: hyperopt >=0.2 ; extra == 'all'
Requires-Dist: storm-tuner ; extra == 'all'
Requires-Dist: scikit-learn >=1.0 ; extra == 'all'
Requires-Dist: tensorflow >=2.0 ; extra == 'all'
Requires-Dist: keras >=2.4 ; extra == 'all'
Requires-Dist: autoimpute >=0.12 ; extra == 'all'
Provides-Extra: data
Requires-Dist: pandas >=0.24 ; extra == 'data'
Requires-Dist: scipy >=1.1 ; extra == 'data'
Provides-Extra: interfaces
Requires-Dist: scikit-learn >=1.0 ; extra == 'interfaces'
Requires-Dist: tensorflow >=2.0 ; extra == 'interfaces'
Requires-Dist: keras >=2.4 ; extra == 'interfaces'
Requires-Dist: autoimpute >=0.12 ; extra == 'interfaces'
Provides-Extra: operation
Requires-Dist: matplotlib >=3.1 ; extra == 'operation'
Requires-Dist: cloudpickle >=1.0 ; extra == 'operation'
Requires-Dist: requests >2.12 ; extra == 'operation'
Requires-Dist: h5py >=2.10 ; extra == 'operation'
Requires-Dist: python-dateutil >=2.6 ; extra == 'operation'
Requires-Dist: hyperopt >=0.2 ; extra == 'operation'
Requires-Dist: storm-tuner ; extra == 'operation'
Provides-Extra: quickstart
Requires-Dist: pandas >=0.24 ; extra == 'quickstart'
Requires-Dist: scipy >=1.1 ; extra == 'quickstart'
Requires-Dist: matplotlib >=3.1 ; extra == 'quickstart'
Requires-Dist: cloudpickle >=1.0 ; extra == 'quickstart'
Requires-Dist: requests >2.12 ; extra == 'quickstart'
Requires-Dist: h5py >=2.10 ; extra == 'quickstart'
Requires-Dist: python-dateutil >=2.6 ; extra == 'quickstart'
Requires-Dist: hyperopt >=0.2 ; extra == 'quickstart'
Requires-Dist: storm-tuner ; extra == 'quickstart'
Requires-Dist: scikit-learn >=1.0 ; extra == 'quickstart'
